rubymarshal/__init__.py
rubymarshal/classes.py
rubymarshal/constants.py
rubymarshal/reader.py
rubymarshal/tests/__init__.py
rubymarshal/tests/mutations.py
rubymarshal/tests/test_bug11.py
rubymarshal/tests/test_hypothesis.py
rubymarshal/tests/test_new_properties.py
rubymarshal/tests/test_reader.py
rubymarshal/tests/test_symbol.py
rubymarshal/tests/test_utils.py
rubymarshal/tests/test_writer.py
rubymarshal/utils.py
rubymarshal/writer.py
rubymarshal-1.2.8.dist-info/LICENSE
rubymarshal-1.2.8.dist-info/METADATA
rubymarshal-1.2.8.dist-info/WHEEL
rubymarshal-1.2.8.dist-info/RECORD
