Metadata-Version: 2.3
Name: rubymarshal
Version: 1.2.8
Summary: Read and write Ruby-marshalled data
Home-page: https://github.com/interdiode/interdiode-logo
License: WTFPL
Author: Matthieu Gallet
Author-email: github@19pouces.net
Maintainer: Matthieu Gallet
Maintainer-email: github@19pouces.net
Requires-Python: >=3.8,<4.0
Classifier: Development Status :: 5 - Production/Stable
Classifier: Intended Audience :: System Administrators
Classifier: License :: OSI Approved
Classifier: License :: Other/Proprietary License
Classifier: Programming Language :: Python :: 3
Classifier: Programming Language :: Python :: 3.8
Classifier: Programming Language :: Python :: 3.9
Classifier: Programming Language :: Python :: 3.10
Classifier: Programming Language :: Python :: 3.11
Classifier: Programming Language :: Python :: 3.12
Classifier: Programming Language :: Python :: 3.13
Classifier: Programming Language :: Python :: 3 :: Only
Classifier: Programming Language :: Python :: 3.6
Classifier: Programming Language :: Python :: 3.7
Classifier: Topic :: Utilities
Project-URL: Documentation, https://github.com/d9pouces/RubyMarshal
Project-URL: Repository, https://github.com/interdiode/interdiode-logo
